openiziai/__init__.py
openiziai/agents/__init__.py
openiziai/agents/agent.py
openiziai/agents/manager.py
openiziai/contexts/__init__.py
openiziai/contexts/contexts.py
openiziai/contexts/handler.py
openiziai/fine_tuning.py
openiziai/schemas.py
openiziai/task.py
openiziai/tools/__init__.py
openiziai/tools/prep_data.py
openiziai/tools/train_data.py
openiziai/utils.py
openiziai-0.1.1.dist-info/LICENSE
openiziai-0.1.1.dist-info/METADATA
openiziai-0.1.1.dist-info/WHEEL
openiziai-0.1.1.dist-info/RECORD
