Metadata-Version: 2.1
Name: openiziai
Version: 0.1.1
Summary: Interface para se comunicar com a api da OpenAI adotando as melhores práticas de LLM para criar e se comunicar com um agente.
License: MIT
Author: RWallan
Author-email: 3am.richardwallan@gmail.com
Requires-Python: >=3.11,<4.0
Classifier: Development Status :: 3 - Alpha
Classifier: Intended Audience :: Developers
Classifier: Intended Audience :: Education
Classifier: License :: OSI Approved :: MIT License
Classifier: Natural Language :: Portuguese (Brazilian)
Classifier: Programming Language :: Python :: 3
Classifier: Programming Language :: Python :: 3.11
Classifier: Programming Language :: Python :: 3.12
Classifier: Topic :: Scientific/Engineering :: Artificial Intelligence
Requires-Dist: openai (>=1.30.1,<2.0.0)
Requires-Dist: pydantic (>=2.7.1,<3.0.0)
Requires-Dist: tqdm (>=4.66.4,<5.0.0)
Requires-Dist: trio (>=0.25.1,<0.26.0)
Project-URL: Bug Tracker, https://github.com/RWallan/openiziai/issues
Project-URL: Code, https://github.com/RWallan/openiziai.git
Project-URL: Document, https://github.com/RWallan/openiziai/blob/main/README.md
